FileWatchdogService/__init__.py
FileWatchdogService/__main__.py
FileWatchdogService/const.py
FileWatchdogService/service.py
pih_file-1.12.dist-info/METADATA
pih_file-1.12.dist-info/WHEEL
pih_file-1.12.dist-info/entry_points.txt
pih_file-1.12.dist-info/top_level.txt
pih_file-1.12.dist-info/RECORD
