Metadata-Version: 2.1
Name: pih-file
Version: 1.12
Summary: PIH FileWatchdog service package
Home-page: https://pacifichosp.com/
Author: Nikita Karachentsev
Author-email: it@pacifichosp.com
License: MIT
Requires-Dist: ipih
Requires-Dist: watchdog
